mots/__init__.py
mots/bmo.py
mots/ci.py
mots/cli.py
mots/config.py
mots/directory.py
mots/export.py
mots/logging.py
mots/mach_interface.py
mots/module.py
mots/pmo.py
mots/settings.py
mots/utils.py
mots/yaml.py
mots/templates/directory.template.md
mots/templates/directory.template.rst
mots-0.13.3.dist-info/licenses/AUTHORS
mots-0.13.3.dist-info/licenses/LICENSE
mots-0.13.3.dist-info/METADATA
mots-0.13.3.dist-info/WHEEL
mots-0.13.3.dist-info/entry_points.txt
mots-0.13.3.dist-info/top_level.txt
mots-0.13.3.dist-info/RECORD
