Metadata-Version: 2.4
Name: mots
Version: 0.13.3
Summary: Module Ownership in Tree System
Home-page: https://github.com/mozilla-conduit/mots
Author: Zeid Zabaneh
Author-email: zeid@mozilla.com
Classifier: License :: OSI Approved :: Mozilla Public License 2.0 (MPL 2.0)
Classifier: Development Status :: 4 - Beta
Classifier: Intended Audience :: Developers
Classifier: Operating System :: OS Independent
Classifier: Programming Language :: Python :: 3
Requires-Python: >=3.8
License-File: LICENSE
License-File: AUTHORS
Requires-Dist: ruamel.yaml==0.17.21
Requires-Dist: importlib-resources>=5.4.0
Requires-Dist: requests>=2.0.0
Requires-Dist: packaging
Requires-Dist: jinja2
Dynamic: license-file
